<ui:UiBinder xmlns:ui='urn:ui:com.google.gwt.uibinder'
             xmlns:g='urn:import:com.google.gwt.user.client.ui'
             xmlns:p='urn:import:com.vaadin.polymer.paper.widget'>

    <g:HTMLPanel addStyleNames="spinner-sample">
        <style is="custom-style">
            .spinner-sample .horizontal-section {
                width: 100px;
            }

            .spinner-sample paper-spinner, button {
                display: block;
                margin-bottom: 24px;
                margin-left: auto;
                margin-right: auto;
            }

            .spinner-sample paper-spinner.blue {
                --paper-spinner-layer-1-color: var(--paper-light-blue-500);
                --paper-spinner-layer-2-color: var(--paper-light-blue-500);
                --paper-spinner-layer-3-color: var(--paper-light-blue-500);
                --paper-spinner-layer-4-color: var(--paper-light-blue-500);
            }

            .spinner-sample paper-spinner.red {
                --paper-spinner-layer-1-color: var(--paper-red-500);
                --paper-spinner-layer-2-color: var(--paper-red-500);
                --paper-spinner-layer-3-color: var(--paper-red-500);
                --paper-spinner-layer-4-color: var(--paper-red-500);
            }

            .spinner-sample paper-spinner.orange {
                --paper-spinner-layer-1-color: var(--paper-orange-500);
                --paper-spinner-layer-2-color: var(--paper-orange-500);
                --paper-spinner-layer-3-color: var(--paper-orange-500);
                --paper-spinner-layer-4-color: var(--paper-orange-500);
            }

            .spinner-sample paper-spinner.green {
                --paper-spinner-layer-1-color: var(--paper-green-500);
                --paper-spinner-layer-2-color: var(--paper-green-500);
                --paper-spinner-layer-3-color: var(--paper-green-500);
                --paper-spinner-layer-4-color: var(--paper-green-500);
            }
        </style>
        <div class="horizontal-section-container center-justified layout">
            <div>
                <h4>Default</h4>
                <div class="horizontal-section">
                    <p:PaperSpinner active="true" ui:field="toggle1_1"/>
                    <p:PaperSpinner active="true" ui:field="toggle1_2"/>
                    <p:PaperSpinner active="true" ui:field="toggle1_3"/>
                    <p:PaperSpinner active="true" ui:field="toggle1_4"/>
                    <g:Button ui:field="toggleBtn1">Toggle</g:Button>
                </div>
            </div>

            <div>
                <h4>Color</h4>
                <div class="horizontal-section">
                    <p:PaperSpinner active="true" ui:field="toggle2_1" addStyleNames="blue"/>
                    <p:PaperSpinner active="true" ui:field="toggle2_2" addStyleNames="red"/>
                    <p:PaperSpinner active="true" ui:field="toggle2_3" addStyleNames="orange"/>
                    <paper-spinner ui:field="toggle2_4" active="" class="green"/>
                    <g:Button ui:field="toggleBtn2">Toggle</g:Button>
                </div>
            </div>
        </div>
    </g:HTMLPanel>
</ui:UiBinder>
